deltabot/__init__.py
deltabot/cmdline.py
deltabot/parse.py
deltabot-0.7.2.dist-info/DESCRIPTION.rst
deltabot-0.7.2.dist-info/LICENSE.txt
deltabot-0.7.2.dist-info/METADATA
deltabot-0.7.2.dist-info/RECORD
deltabot-0.7.2.dist-info/WHEEL
deltabot-0.7.2.dist-info/entry_points.txt
deltabot-0.7.2.dist-info/metadata.json
deltabot-0.7.2.dist-info/top_level.txt
