Metadata-Version: 2.0
Name: deltabot
Version: 0.7.2
Summary: Delta.Chat bot to reply to incoming messages in groups or 1:1 chats
Home-page: https://github.com/hpk42/deltabot
Author: holger krekel
Author-email: holger@merlinux.eu
License: GPL
Platform: unix
Platform: linux
Platform: osx
Platform: cygwin
Platform: win32
Classifier: Development Status :: 3 - Alpha
Classifier: Intended Audience :: Developers
Classifier: License :: OSI Approved :: MIT License
Classifier: Operating System :: POSIX
Classifier: Operating System :: MacOS :: MacOS X
Classifier: Topic :: Utilities
Classifier: Intended Audience :: Developers
Classifier: Programming Language :: Python
Requires-Dist: click (>=6.0)
Requires-Dist: deltachat (>=0.8.0)
